{
  "type": "peaks:peak_gen",
  "config": {
    "radius": 5,
    "delta_radius": 4,

    "top_height_multiplier": 0.75,

    "bottom_height_multiplier": 0.75,
    "bottom_deposit": {
      "provider" : {
        "type": "peaks:compat_priority_selector",
        "blocks": ["railcraft:zinc_block"]
      }
    },

    "cylindrical_surfaces": [
      {
        "min_radius": 0.25,
        "max_radius": 1.0,
        "targets": [
          {
            "provider" : {
              "type": "peaks:compat_priority_selector",
              "blocks": ["railcraft:zinc_ore"]
            },
            "target": {
              "predicate_type": "minecraft:tag_match",
              "tag": "minecraft:stone_ore_replaceables"
            }
          },
          {
            "provider" : {
              "type": "peaks:compat_priority_selector",
              "blocks": ["railcraft:deepslate_zinc_ore"]
            },
            "target": {
              "predicate_type": "minecraft:tag_match",
              "tag": "minecraft:deepslate_ore_replaceables"
            }
          }
        ]
      }
    ]
  }
}